{
  "scriptId": "513",
  "url": "file:///C:/Users/micha_8ygdgy8/AppData/Local/deno/npm/registry.npmjs.org/retry/0.13.1/lib/retry_operation.js",
  "functions": [
    {
      "functionName": "",
      "ranges": [{ "startOffset": 0, "endOffset": 4037, "count": 1 }],
      "isBlockCoverage": true
    },
    {
      "functionName": "",
      "ranges": [{ "startOffset": 1, "endOffset": 4036, "count": 1 }],
      "isBlockCoverage": true
    },
    {
      "functionName": "",
      "ranges": [{ "startOffset": 194, "endOffset": 3972, "count": 1 }],
      "isBlockCoverage": true
    },
    {
      "functionName": "RetryOperation",
      "ranges": [
        { "startOffset": 254, "endOffset": 935, "count": 3 },
        { "startOffset": 401, "endOffset": 442, "count": 0 },
        { "startOffset": 564, "endOffset": 569, "count": 0 },
        { "startOffset": 876, "endOffset": 933, "count": 0 }
      ],
      "isBlockCoverage": true
    },
    {
      "functionName": "RetryOperation.reset",
      "ranges": [{ "startOffset": 1003, "endOffset": 1091, "count": 0 }],
      "isBlockCoverage": false
    },
    {
      "functionName": "RetryOperation.stop",
      "ranges": [{ "startOffset": 1125, "endOffset": 1316, "count": 0 }],
      "isBlockCoverage": false
    },
    {
      "functionName": "RetryOperation.retry",
      "ranges": [
        { "startOffset": 1352, "endOffset": 2478, "count": 6 },
        { "startOffset": 1389, "endOffset": 1427, "count": 0 },
        { "startOffset": 1441, "endOffset": 1464, "count": 0 },
        { "startOffset": 1578, "endOffset": 1701, "count": 0 },
        { "startOffset": 1799, "endOffset": 2023, "count": 1 },
        { "startOffset": 1831, "endOffset": 1986, "count": 0 },
        { "startOffset": 2023, "endOffset": 2428, "count": 5 },
        { "startOffset": 2428, "endOffset": 2460, "count": 0 },
        { "startOffset": 2460, "endOffset": 2477, "count": 5 }
      ],
      "isBlockCoverage": true
    },
    {
      "functionName": "",
      "ranges": [
        { "startOffset": 2071, "endOffset": 2388, "count": 5 },
        { "startOffset": 2141, "endOffset": 2353, "count": 0 }
      ],
      "isBlockCoverage": true
    },
    {
      "functionName": "",
      "ranges": [{ "startOffset": 2176, "endOffset": 2246, "count": 0 }],
      "isBlockCoverage": false
    },
    {
      "functionName": "RetryOperation.attempt",
      "ranges": [
        { "startOffset": 2516, "endOffset": 2997, "count": 3 },
        { "startOffset": 2579, "endOffset": 2750, "count": 0 },
        { "startOffset": 2803, "endOffset": 2918, "count": 0 }
      ],
      "isBlockCoverage": true
    },
    {
      "functionName": "",
      "ranges": [{ "startOffset": 2836, "endOffset": 2888, "count": 0 }],
      "isBlockCoverage": false
    },
    {
      "functionName": "RetryOperation.try",
      "ranges": [{ "startOffset": 3031, "endOffset": 3126, "count": 0 }],
      "isBlockCoverage": false
    },
    {
      "functionName": "RetryOperation.start",
      "ranges": [{ "startOffset": 3162, "endOffset": 3259, "count": 0 }],
      "isBlockCoverage": false
    },
    {
      "functionName": "RetryOperation.errors",
      "ranges": [{ "startOffset": 3360, "endOffset": 3397, "count": 0 }],
      "isBlockCoverage": false
    },
    {
      "functionName": "RetryOperation.attempts",
      "ranges": [{ "startOffset": 3436, "endOffset": 3475, "count": 0 }],
      "isBlockCoverage": false
    },
    {
      "functionName": "RetryOperation.mainError",
      "ranges": [
        { "startOffset": 3515, "endOffset": 3968, "count": 1 },
        { "startOffset": 3561, "endOffset": 3583, "count": 0 },
        { "startOffset": 3703, "endOffset": 3945, "count": 6 },
        { "startOffset": 3804, "endOffset": 3808, "count": 1 }
      ],
      "isBlockCoverage": true
    }
  ]
}
